sbtc_gateway/__init__.py
sbtc_gateway/api_key.py
sbtc_gateway/base.py
sbtc_gateway/client.py
sbtc_gateway/exceptions.py
sbtc_gateway/merchant.py
sbtc_gateway/payments.py
sbtc_gateway/types.py
sbtc_gateway/webhook_api.py
sbtc_gateway/webhooks.py
stacks_pay_python-1.0.0.dist-info/licenses/LICENSE
stacks_pay_python-1.0.0.dist-info/METADATA
stacks_pay_python-1.0.0.dist-info/WHEEL
stacks_pay_python-1.0.0.dist-info/top_level.txt
stacks_pay_python-1.0.0.dist-info/RECORD
