Metadata-Version: 2.4
Name: stacks-pay-python
Version: 1.0.0
Summary: Official Python SDK for StacksPay - Accept Bitcoin and STX payments
Author-email: StacksPay Team <developers@stackspay.com>
Maintainer-email: StacksPay Team <developers@stackspay.com>
License: MIT
Project-URL: Homepage, https://stackspay.com
Project-URL: Documentation, https://docs.stackspay.com
Project-URL: Repository, https://github.com/TheSoftNode/sbtc-payment-gateway
Project-URL: Issues, https://github.com/TheSoftNode/sbtc-payment-gateway/issues
Keywords: bitcoin,stacks,sbtc,payments,crypto,gateway,api,sdk
Classifier: Development Status :: 5 - Production/Stable
Classifier: Intended Audience :: Developers
Classifier: Operating System :: OS Independent
Classifier: Programming Language :: Python :: 3
Classifier: Programming Language :: Python :: 3.8
Classifier: Programming Language :: Python :: 3.9
Classifier: Programming Language :: Python :: 3.10
Classifier: Programming Language :: Python :: 3.11
Classifier: Programming Language :: Python :: 3.12
Classifier: Topic :: Software Development :: Libraries :: Python Modules
Classifier: Topic :: Internet :: WWW/HTTP
Classifier: Topic :: Office/Business :: Financial
Requires-Python: >=3.8
License-File: LICENSE
Requires-Dist: requests>=2.28.0
Requires-Dist: typing-extensions>=4.0.0; python_version < "3.8"
Provides-Extra: dev
Requires-Dist: pytest>=7.0.0; extra == "dev"
Requires-Dist: pytest-cov>=4.0.0; extra == "dev"
Requires-Dist: black>=22.0.0; extra == "dev"
Requires-Dist: flake8>=5.0.0; extra == "dev"
Requires-Dist: mypy>=1.0.0; extra == "dev"
Requires-Dist: isort>=5.0.0; extra == "dev"
Dynamic: license-file
